synkroni/__init__.py
synkroni/json.py
synkroni/komennot.py
synkroni/mallit.py
synkroni/models.py
synkroni/synkroni.py
synkroni/toiminnot.py
synkroni/websocket.py
synkroni/static/synkroni/js/synkroni.js
synkroni/templates/synkroni/synkroni.html
django_synkroni-0.5.2.dist-info/METADATA
django_synkroni-0.5.2.dist-info/WHEEL
django_synkroni-0.5.2.dist-info/entry_points.txt
django_synkroni-0.5.2.dist-info/historia.json
django_synkroni-0.5.2.dist-info/top_level.txt
django_synkroni-0.5.2.dist-info/RECORD
