Metadata-Version: 2.1
Name: django-synkroni
Version: 0.5.2
Summary: Django/Javascript-synkronointirajapinta
Home-page: https://github.com/an7oine/django-synkroni.git
Author: Antti Hautaniemi
Author-email: antti.hautaniemi@me.com
License: MIT
Requires-Dist: django >=3.1
Requires-Dist: django-pistoke >=0.8c1
